somali_stopwords/__init__.py
somali_stopwords/stopwords.py
somali_stopwords-0.1.dist-info/METADATA
somali_stopwords-0.1.dist-info/WHEEL
somali_stopwords-0.1.dist-info/top_level.txt
somali_stopwords-0.1.dist-info/RECORD
