Metadata-Version: 2.1
Name: somali-stopwords
Version: 0.1
Summary: A library to handle Somali stopwords
Author: R&D
Author-email: abdoldevtra@gmail.com
